[
  {
    "username": "joao",
    "email": "joao@gmail.com",
    "password": "123"
  },
  {
    "username": "maria",
    "email": "maria@gmail.com",
    "password": "12345"
  },
  {
    "username": "teste2",
    "email": "teste2@teste.com",
    "password": "1234"
  },
  {},
  {
    "username": "test",
    "email": "test@test.com",
    "password": "12345"
  },
  {
    "username": "sara",
    "email": "sara@gmail.com",
    "password": "4321"
  },
  {
    "username": "teste",
    "email": "teste@teste",
    "password": "1212"
  },
  {
    "username": "novoteste",
    "email": "novoteste@teste.com",
    "password": "1111"
  },
  {
    "username": "ivan",
    "email": "ivan@gmail.com",
    "password": "1114"
  },
  {
    "username": "Caio",
    "email": "caio@gmail.com",
    "password": "1313"
  }
]